teamFormationLibrary/TFL.py
teamFormationLibrary/VAE.py
teamFormationLibrary/__init__.py
teamFormationLibrary/__main__.py
teamFormationLibrary/config.txt
teamFormationLibrary/example.py
teamFormationLibrary/dal/__init__.py
teamFormationLibrary/dal/embedding.py
teamFormationLibrary/dal/load_dblp_data.py
teamFormationLibrary/dal/readme.md
teamFormationLibrary/dataset/ae_t2v_dim100_tSkill_dataset.pkl
teamFormationLibrary/dataset/dblp_preprocessed_dataset.pkl
teamFormationLibrary/dataset/readme.md
teamFormationLibrary/eval/__init__.py
teamFormationLibrary/eval/evaluation.py
teamFormationLibrary/eval/ranking.py
teamFormationLibrary/eval/readme.md
teamFormationLibrary/output/readme.md
teamFormationLibrary/output/diagrams/metric_fig.png
teamFormationLibrary/output/predictions/S_VAE_O_output.csv
teamFormationLibrary/output/predictions/correlation_baseline_output.csv
teamFormationLibrary/output/train_test_indices/test_indices.csv
teamFormationLibrary/output/train_test_indices/train_indices.csv
teamFormationLibrary/util/__init__.py
teamFormationLibrary/util/readme.md
teamFormationLibrary/util/variational.py
pytfl-1.0.1.dist-info/METADATA
pytfl-1.0.1.dist-info/WHEEL
pytfl-1.0.1.dist-info/top_level.txt
pytfl-1.0.1.dist-info/RECORD
