Metadata-Version: 2.1
Name: pytfl
Version: 1.0.1
Summary: Team Formation Library with Tensorflow Machine Learning
Home-page: https://github.com/radinhamidi/Team_Formation_Library/
Author: Radin Hamidi, Aabid Mitha
Author-email: radin@ryerson.ca
License: MIT
Platform: UNKNOWN
Classifier: License :: OSI Approved :: MIT License
Classifier: Programming Language :: Python :: 3.6
Requires-Dist: tensorflow (==1.15.0)
Requires-Dist: keras (==2.0.0)
Requires-Dist: gensim
Requires-Dist: nltk (==3.5)
Requires-Dist: scikit-learn
Requires-Dist: sklearn
